tyssue/__init__.py
tyssue/version.py
tyssue/behaviors/__init__.py
tyssue/behaviors/event_manager.py
tyssue/behaviors/monolayer/__init__.py
tyssue/behaviors/monolayer/actions.py
tyssue/behaviors/monolayer/apoptosis_events.py
tyssue/behaviors/monolayer/basic_events.py
tyssue/behaviors/monolayer/delamination_events.py
tyssue/behaviors/sheet/__init__.py
tyssue/behaviors/sheet/actions.py
tyssue/behaviors/sheet/apoptosis_events.py
tyssue/behaviors/sheet/basic_events.py
tyssue/behaviors/sheet/delamination_events.py
tyssue/collisions/__init__.py
tyssue/collisions/intersection.py
tyssue/collisions/solvers.py
tyssue/collisions/cpp/__init__.py
tyssue/config/__init__.py
tyssue/config/json_parser.py
tyssue/config/core/__init__.py
tyssue/config/core/core.json
tyssue/config/draw/__init__.py
tyssue/config/draw/sheet.json
tyssue/config/dynamics/__init__.py
tyssue/config/dynamics/bulk_qs.json
tyssue/config/dynamics/ccmesh.json
tyssue/config/dynamics/plane_qs.json
tyssue/config/dynamics/sheet_qs.json
tyssue/config/dynamics/sheet_qs_anchor.json
tyssue/config/geometry/__init__.py
tyssue/config/geometry/bulk.json
tyssue/config/geometry/cylindrical_sheet.json
tyssue/config/geometry/flat_sheet.json
tyssue/config/geometry/planar.json
tyssue/config/geometry/rod_sheet.json
tyssue/config/geometry/sheet.json
tyssue/config/geometry/spherical_sheet.json
tyssue/config/solvers/__init__.py
tyssue/config/solvers/minimize.json
tyssue/config/solvers/sheet.json
tyssue/config/stores/__init__.py
tyssue/config/stores/planar_periodic8x8.json
tyssue/config/subdiv/__init__.py
tyssue/config/subdiv/bulk.json
tyssue/core/__init__.py
tyssue/core/history.py
tyssue/core/monolayer.py
tyssue/core/multisheet.py
tyssue/core/objects.py
tyssue/core/sheet.py
tyssue/draw/__init__.py
tyssue/draw/ipv_draw.py
tyssue/draw/plt_draw.py
tyssue/draw/vispy_draw.py
tyssue/dynamics/__init__.py
tyssue/dynamics/apoptosis_model.py
tyssue/dynamics/base_gradients.py
tyssue/dynamics/bulk_gradients.py
tyssue/dynamics/bulk_model.py
tyssue-0.8.0.dist-info/LICENSE
tyssue-0.8.0.dist-info/METADATA
tyssue-0.8.0.dist-info/WHEEL
tyssue-0.8.0.dist-info/top_level.txt
tyssue-0.8.0.dist-info/RECORD
