Metadata-Version: 2.1
Name: tyssue
Version: 0.8.0
Summary: tyssue is a living tissues, cell level, modeling library
Home-page: https://github.com/DamCB/tyssue
Maintainer: Guillaume Gay
Maintainer-email: guillaume@damcb.com
License: GPL-3.0
Download-URL: https://github.com/DamCB/tyssue.git
Platform: UNKNOWN
Classifier: Development Status :: 4 - Beta
Classifier: Intended Audience :: Science/Research
Classifier: License :: OSI Approved :: GNU General Public License v3 (GPLv3)
Classifier: Natural Language :: English
Classifier: Operating System :: MacOS
Classifier: Operating System :: Microsoft
Classifier: Operating System :: POSIX :: Linux
Classifier: Programming Language :: Python
Classifier: Topic :: Scientific/Engineering :: Bio-Informatics
Classifier: Topic :: Scientific/Engineering :: Medical Science Apps.
Classifier: Topic :: Scientific/Engineering :: Physics
